plotly_charts/__init__.py
plotly_charts/plot.py
plotly_charts-0.4.dist-info/METADATA
plotly_charts-0.4.dist-info/WHEEL
plotly_charts-0.4.dist-info/top_level.txt
plotly_charts-0.4.dist-info/RECORD
