Metadata-Version: 2.1
Name: plotly-charts
Version: 0.4
Summary: Helper functions for plotly charts
Home-page: http://github.com/walkerlangley/plotly-charts#v0.4
Author: Walker Langley
Author-email: flyingcircus@example.com
License: MIT
Platform: UNKNOWN
Requires-Dist: plotly
Requires-Dist: pandas
Requires-Dist: datetime
Requires-Dist: cufflinks
Requires-Dist: numpy
